heartcv/__init__.py
heartcv/conftest.py
heartcv/heartcv.py
heartcv/data/sample.avi
heartcv-0.2.0.post1.dist-info/METADATA
heartcv-0.2.0.post1.dist-info/WHEEL
heartcv-0.2.0.post1.dist-info/top_level.txt
heartcv-0.2.0.post1.dist-info/RECORD
