Metadata-Version: 2.1
Name: heartcv
Version: 0.2.0.post1
Summary: Automated, noninvasive quantification of cardiac traits in transparent animals.
Home-page: https://github.com/EmbryoPhenomics/heartcv
Author: Ziad Ibbini, John I. Spicer, Manuela Truebano, John Bishop, Oliver Tills
Author-email: ziad.ibbini@students.plymouth.ac.uk
License: MIT
Project-URL: Source, https://github.com/EmbryoPhenomics/heartcv/tree/main/heartcv
Requires-Python: >=3.5, <4
Requires-Dist: vuba
Requires-Dist: numpy
Requires-Dist: scipy
Requires-Dist: more-itertools
Requires-Dist: numba
Requires-Dist: matplotlib
Requires-Dist: tqdm
Requires-Dist: pytest
Requires-Dist: scikit-image
Requires-Dist: wget
